undictify/__init__.py
undictify/_unpack.py
undictify/py.typed
undictify/tests.py
undictify-0.11.3.dist-info/LICENSE
undictify-0.11.3.dist-info/METADATA
undictify-0.11.3.dist-info/WHEEL
undictify-0.11.3.dist-info/top_level.txt
undictify-0.11.3.dist-info/RECORD
