Metadata-Version: 2.1
Name: undictify
Version: 0.11.3
Summary: Type-checked function calls at runtime
Home-page: http://github.com/Dobiasd/undictify
Author: Tobias Hermann
Author-email: editgym@gmail.com
License: UNKNOWN
Platform: UNKNOWN
Classifier: Programming Language :: Python :: 3.7
Classifier: Programming Language :: Python :: 3.8
Classifier: Programming Language :: Python :: 3.9
Classifier: License :: OSI Approved :: MIT License
Classifier: Operating System :: OS Independent
